moat/dev/heat/__init__.py
moat/dev/heat/_main.py
moat/dev/heat/kwb.py
moat/dev/heat/solvis.py
moat_dev_heat-0.1.5.dist-info/licenses/LICENSE.txt
moat_dev_heat-0.1.5.dist-info/METADATA
moat_dev_heat-0.1.5.dist-info/WHEEL
moat_dev_heat-0.1.5.dist-info/top_level.txt
moat_dev_heat-0.1.5.dist-info/RECORD
