Metadata-Version: 2.4
Name: moat-dev-heat
Version: 0.1.5
Summary: REPLACE ME
Author-email: Matthias Urlichs <matthias@urlichs.de>
Project-URL: homepage, https://m-o-a-t.org
Project-URL: repository, https://github.com/M-o-a-T/moat
Keywords: MoaT
Classifier: Development Status :: 4 - Beta
Classifier: Framework :: AnyIO
Classifier: Framework :: Trio
Classifier: Framework :: AsyncIO
Classifier: Programming Language :: Python :: 3
Classifier: Intended Audience :: Developers
Requires-Python: >=3.8
License-File: LICENSE.txt
Requires-Dist: anyio~=4.2
Requires-Dist: aionotify
Requires-Dist: moat-lib-pid~=0.6.6
Requires-Dist: moat-lib-run~=0.1.0
Requires-Dist: moat-util~=0.61.1
Dynamic: license-file
